morphio/_morphio.cpython-312-x86_64-linux-gnu.so
morphio/__init__.py
morphio/vasculature/__init__.py
morphio/mut/__init__.py
morphio-3.4.0.dist-info/LICENSE.txt
morphio-3.4.0.dist-info/top_level.txt
morphio-3.4.0.dist-info/RECORD
morphio-3.4.0.dist-info/METADATA
morphio-3.4.0.dist-info/WHEEL
morphio-3.4.0.dist-info/AUTHORS.txt
