Metadata-Version: 2.1
Name: morphio
Version: 3.4.0
Summary: A neuron morphology IO library
Home-page: https://github.com/BlueBrain/MorphIO/
Author: Blue Brain Project, EPFL
License: Apache License 2.0
Keywords: computational neuroscience,morphology,neuron,neurolucida,neuromorphology
Classifier: Intended Audience :: Education
Classifier: Intended Audience :: Science/Research
Classifier: Programming Language :: Python
Classifier: Topic :: Scientific/Engineering :: Bio-Informatics
Requires-Python: >=3.8
Provides-Extra: docs
License-File: LICENSE.txt
License-File: AUTHORS.txt
